email_accounts/__init__.py
email_accounts/admin.py
email_accounts/api_urls.py
email_accounts/apps.py
email_accounts/filters.py
email_accounts/forms.py
email_accounts/models.py
email_accounts/serializers.py
email_accounts/urls.py
email_accounts/utils.py
email_accounts/views.py
email_accounts/static/css/style.css
email_accounts/templates/email_accounts/login.html
email_accounts/templates/email_accounts/register.html
email_accounts/templates/email_accounts/password/change/1.html
email_accounts/templates/email_accounts/password/change/2.html
email_accounts/templates/email_accounts/password/reset/1.html
email_accounts/templates/email_accounts/password/reset/2.html
email_accounts/templates/email_accounts/password/reset/3.html
email_accounts/templates/email_accounts/password/reset/4.html
django_email_accounts-0.7.0.dist-info/LICENSE
django_email_accounts-0.7.0.dist-info/METADATA
django_email_accounts-0.7.0.dist-info/WHEEL
django_email_accounts-0.7.0.dist-info/top_level.txt
django_email_accounts-0.7.0.dist-info/RECORD
