Metadata-Version: 2.1
Name: django-email-accounts
Version: 0.7.0
Summary: A Django app for user management with email-based authentication.
Home-page: https://github.com/fathiabdelmalek/django-email-accounts
Author: Fathi Abdelmalek
Author-email: abdelmalek.fathi.2001@gmail.com
License: OSI Approved :: GNU General Public License v3 (GPLv3)
Classifier: Development Status :: 4 - Beta
Classifier: Framework :: Django
Classifier: Intended Audience :: Developers
Classifier: License :: OSI Approved :: GNU General Public License v3 (GPLv3)
Classifier: Operating System :: OS Independent
Classifier: Programming Language :: Python
Classifier: Programming Language :: Python :: 3
Classifier: Topic :: Internet
Classifier: Topic :: Software Development
Requires-Python: >=3.6
License-File: LICENSE
Requires-Dist: Django
Provides-Extra: filters
Requires-Dist: django-filter ; extra == 'filters'
Provides-Extra: rest_framework
Requires-Dist: djangorestframework ; extra == 'rest_framework'
